remote/__init__.py
remote/consumer.py
remote/producer.py
remote/py.typed
remote/util.py
rmq_remote-0.1.0.dist-info/LICENSE
rmq_remote-0.1.0.dist-info/METADATA
rmq_remote-0.1.0.dist-info/WHEEL
rmq_remote-0.1.0.dist-info/RECORD
