Metadata-Version: 2.3
Name: rmq-remote
Version: 0.1.0
Summary: Remote Procedure Call (RPC) library for Python using RabbitMQ
License: Apache-2.0
Keywords: remote procedure call,rpc,rabbitmq,asyncio,python,library
Author: mk
Author-email: mk@plataux.com
Requires-Python: >3.9.1,<4
Classifier: License :: OSI Approved :: Apache Software License
Classifier: Operating System :: OS Independent
Classifier: Programming Language :: Python :: 3
Classifier: Programming Language :: Python :: 3.10
Classifier: Programming Language :: Python :: 3.11
Classifier: Programming Language :: Python :: 3.12
Classifier: Programming Language :: Python :: 3.13
Classifier: Topic :: Software Development :: Build Tools
Classifier: Topic :: Software Development :: Libraries :: Python Modules
Requires-Dist: aio_pika (>=9.4,<10.0)
Project-URL: Homepage, https://github.com/plataux/remote
Project-URL: Repository, https://github.com/plataux/remote
